seamlesspass/__init__.py
seamlesspass/banner.py
seamlesspass/main.py
seamlesspass/seamlesspass.py
seamlesspass/utils/__init__.py
seamlesspass/utils/exceptions.py
seamlesspass/utils/help_formatter.py
seamlesspass/utils/helper.py
seamlesspass/utils/kerberos.py
seamlesspass/utils/log.py
seamlesspass/utils/microsoft365.py
seamlesspass/utils/ticketer.py
seamlesspass-0.0.1.dist-info/LICENSE
seamlesspass-0.0.1.dist-info/METADATA
seamlesspass-0.0.1.dist-info/WHEEL
seamlesspass-0.0.1.dist-info/entry_points.txt
seamlesspass-0.0.1.dist-info/top_level.txt
seamlesspass-0.0.1.dist-info/RECORD
