Metadata-Version: 2.1
Name: seamlesspass
Version: 0.0.1
Summary: Leveraging Kerberos tickets to get cloud access tokens using Seamless SSO
Home-page: https://github.com/malcrove/SeamlessPass
Author: 0xSyndr0me
License: MIT
Classifier: Programming Language :: Python :: 3
Classifier: License :: OSI Approved :: MIT License
Classifier: Operating System :: OS Independent
License-File: LICENSE
Requires-Dist: pyasn1
Requires-Dist: impacket
Requires-Dist: requests
Requires-Dist: colorama
